tob/__init__.py
tob/__main__.py
tob/broker.py
tob/client.py
tob/cmnd.py
tob/config.py
tob/disk.py
tob/engine.py
tob/event.py
tob/json.py
tob/kernel.py
tob/log.py
tob/method.py
tob/object.py
tob/path.py
tob/pkg.py
tob/static.py
tob/thread.py
tob/time.py
tob/utils.py
tob/modules/__init__.py
tob/modules/atr.py
tob/modules/flt.py
tob/modules/fnd.py
tob/modules/irc.py
tob/modules/log.py
tob/modules/lst.py
tob/modules/mod.py
tob/modules/rss.py
tob/modules/sil.py
tob/modules/tdo.py
tob/modules/thr.py
tob/modules/tmr.py
tob/modules/udp.py
tob/modules/upt.py
tob-150.dist-info/METADATA
tob-150.dist-info/WHEEL
tob-150.dist-info/entry_points.txt
tob-150.dist-info/top_level.txt
tob-150.dist-info/RECORD
