Metadata-Version: 2.4
Name: tob
Version: 150
Summary: bot library.
Author-email: Bart Thate <bthate@dds.nl>
License-Expression: Unlicense
Project-URL: home, https://pypi.org/project/tob
Project-URL: bugs, https://github.com/botlibX/tob/issues
Project-URL: source, https://github.com/botlibX/tob
Classifier: Development Status :: 3 - Alpha
Classifier: Operating System :: Unix
Classifier: Programming Language :: Python :: 3
Classifier: Topic :: Utilities
